jiradumper/__init__.py
jiradumper/jiradumper.py
jiradumper-0.2.3.dist-info/entry_points.txt
jiradumper-0.2.3.dist-info/WHEEL
jiradumper-0.2.3.dist-info/METADATA
jiradumper-0.2.3.dist-info/RECORD
