Metadata-Version: 2.1
Name: jiradumper
Version: 0.2.3
Summary: 
Author: Khalid
Author-email: khalidck@gmail.com
Requires-Python: >=3.7,<4.0
Classifier: Programming Language :: Python :: 3
Classifier: Programming Language :: Python :: 3.7
Classifier: Programming Language :: Python :: 3.8
Requires-Dist: click (>=7.1.1,<8.0.0)
Requires-Dist: jira (>=2.0.0,<3.0.0)
Requires-Dist: jsonschema (>=3.2.0,<4.0.0)
